<annotation verified="no">
  <folder>train</folder>
  <filename>000139</filename>
  <path>D:\sentinel\JPEGImages\train\000139.jpg</path>
  <source>
    <database>Unknown</database>
  </source>
  <size>
    <width>256</width>
    <height>256</height>
    <depth>3</depth>
  </size>
  <segmented>0</segmented>
  <object>
    <type>robndbox</type>
    <name>ship</name>
    <pose>Unspecified</pose>
    <truncated>0</truncated>
    <difficult>0</difficult>
    <robndbox>
      <cx>159.5</cx>
      <cy>13.4915</cy>
      <w>8.2418</w>
      <h>19.3409</h>
      <angle>0.355248</angle>
    </robndbox>
  </object>
  <object>
    <type>robndbox</type>
    <name>ship</name>
    <pose>Unspecified</pose>
    <truncated>0</truncated>
    <difficult>0</difficult>
    <robndbox>
      <cx>212.0</cx>
      <cy>73.4915</cy>
      <w>9.5152</w>
      <h>25.5824</h>
      <angle>0.503166</angle>
    </robndbox>
  </object>
  <object>
    <type>robndbox</type>
    <name>ship</name>
    <pose>Unspecified</pose>
    <truncated>0</truncated>
    <difficult>0</difficult>
    <robndbox>
      <cx>142.5</cx>
      <cy>97.9915</cy>
      <w>7.6617</w>
      <h>22.7662</h>
      <angle>0.282992</angle>
    </robndbox>
  </object>
  <object>
    <type>robndbox</type>
    <name>ship</name>
    <pose>Unspecified</pose>
    <truncated>0</truncated>
    <difficult>0</difficult>
    <robndbox>
      <cx>83.0</cx>
      <cy>26.4915</cy>
      <w>7.8095</w>
      <h>25.9232</h>
      <angle>0.218669</angle>
    </robndbox>
  </object>
  <object>
    <type>robndbox</type>
    <name>ship</name>
    <pose>Unspecified</pose>
    <truncated>0</truncated>
    <difficult>0</difficult>
    <robndbox>
      <cx>123.0</cx>
      <cy>172.9915</cy>
      <w>7.5353</w>
      <h>21.0528</h>
      <angle>0.163865</angle>
    </robndbox>
  </object>
  <object>
    <type>robndbox</type>
    <name>ship</name>
    <pose>Unspecified</pose>
    <truncated>0</truncated>
    <difficult>0</difficult>
    <robndbox>
      <cx>46.9112</cx>
      <cy>161.6713</cy>
      <w>9.2112</w>
      <h>19.6467</h>
      <angle>0.261326</angle>
    </robndbox>
  </object>
  <object>
    <type>robndbox</type>
    <name>ship</name>
    <pose>Unspecified</pose>
    <truncated>0</truncated>
    <difficult>0</difficult>
    <robndbox>
      <cx>229.5503</cx>
      <cy>7.9099</cy>
      <w>6.7026</w>
      <h>12.4715</h>
      <angle>0.371578</angle>
    </robndbox>
  </object>
</annotation>