<annotation verified="no">
  <folder>S1B_IW_SLC__1SDV_20210331T154731_20210331T154759_026261_032256_5A64_Cal_deb_mat_ML_RGB</folder>
  <filename>S1B_IW_SLC__1SDV_20210331T154731_20210331T154759_026261_032256_5A64_Cal_deb_mat_ML_RGB_9_1_0_768</filename>
  <path>D:\sentinel\patch\S1B_IW_SLC__1SDV_20210331T154731_20210331T154759_026261_032256_5A64_Cal_deb_mat_ML_RGB\S1B_IW_SLC__1SDV_20210331T154731_20210331T154759_026261_032256_5A64_Cal_deb_mat_ML_RGB_9_1_0_768.png</path>
  <source>
    <database>Unknown</database>
  </source>
  <size>
    <width>256</width>
    <height>256</height>
    <depth>3</depth>
  </size>
  <segmented>0</segmented>
  <object>
    <type>robndbox</type>
    <name>ship</name>
    <pose>Unspecified</pose>
    <truncated>0</truncated>
    <difficult>0</difficult>
    <robndbox>
      <cx>200.6302</cx>
      <cy>56.63040000000001</cy>
      <w>6.9834</w>
      <h>25.2803</h>
      <angle>3.072641</angle>
    </robndbox>
  </object>
  <object>
    <type>robndbox</type>
    <name>ship</name>
    <pose>Unspecified</pose>
    <truncated>0</truncated>
    <difficult>0</difficult>
    <robndbox>
      <cx>95.9845</cx>
      <cy>59.0</cy>
      <w>7.0263</w>
      <h>21.2281</h>
      <angle>0.139786</angle>
    </robndbox>
  </object>
  <object>
    <type>robndbox</type>
    <name>ship</name>
    <pose>Unspecified</pose>
    <truncated>0</truncated>
    <difficult>0</difficult>
    <robndbox>
      <cx>28.9845</cx>
      <cy>74.0</cy>
      <w>8.0</w>
      <h>18.0</h>
      <angle>0.0</angle>
    </robndbox>
  </object>
  <object>
    <type>robndbox</type>
    <name>ship</name>
    <pose>Unspecified</pose>
    <truncated>0</truncated>
    <difficult>0</difficult>
    <robndbox>
      <cx>139.9845</cx>
      <cy>139.0</cy>
      <w>6.0</w>
      <h>18.0</h>
      <angle>0.0</angle>
    </robndbox>
  </object>
  <object>
    <type>robndbox</type>
    <name>ship</name>
    <pose>Unspecified</pose>
    <truncated>0</truncated>
    <difficult>0</difficult>
    <robndbox>
      <cx>190.9845</cx>
      <cy>153.5</cy>
      <w>8.0</w>
      <h>23.0</h>
      <angle>0.0</angle>
    </robndbox>
  </object>
  <object>
    <type>robndbox</type>
    <name>ship</name>
    <pose>Unspecified</pose>
    <truncated>0</truncated>
    <difficult>0</difficult>
    <robndbox>
      <cx>26.9845</cx>
      <cy>172.0</cy>
      <w>6.1223</w>
      <h>17.393</h>
      <angle>0.093474</angle>
    </robndbox>
  </object>
  <object>
    <type>robndbox</type>
    <name>ship</name>
    <pose>Unspecified</pose>
    <truncated>0</truncated>
    <difficult>0</difficult>
    <robndbox>
      <cx>95.4845</cx>
      <cy>219.0</cy>
      <w>7.0</w>
      <h>14.0</h>
      <angle>0.0</angle>
    </robndbox>
  </object>
  </annotation>